readgroup_json_db/__init__.py
readgroup_json_db/__main__.py
readgroup_json_db/main.py
readgroup_json_db-0.14.dist-info/DESCRIPTION.rst
readgroup_json_db-0.14.dist-info/METADATA
readgroup_json_db-0.14.dist-info/RECORD
readgroup_json_db-0.14.dist-info/WHEEL
readgroup_json_db-0.14.dist-info/metadata.json
readgroup_json_db-0.14.dist-info/top_level.txt
