Metadata-Version: 2.0
Name: readgroup-json-db
Version: 0.14
Summary: read readgroup data as json and store in sqlitedb
Home-page: https://github.com/jeremiahsavage/readgroup_json_db
Author: Jeremiah H. Savage
Author-email: jeremiahsavage@gmail.com
License: Apache 2.0
Platform: UNKNOWN
Classifier: Development Status :: 3 - Alpha
Classifier: Intended Audience :: Developers
Classifier: License :: OSI Approved :: Apache Software License
Classifier: Programming Language :: Python
Classifier: Programming Language :: Python :: 2
Classifier: Programming Language :: Python :: 3
Requires-Dist: cdis-pipe-utils
Requires-Dist: pandas
Requires-Dist: sqlalchemy
